test/__init__.py
test/test.py
transep/__init__.py
transep/_version.py
transep/transep.py
transep-1.0.3.dist-info/LICENSE
transep-1.0.3.dist-info/METADATA
transep-1.0.3.dist-info/WHEEL
transep-1.0.3.dist-info/top_level.txt
transep-1.0.3.dist-info/RECORD
