Metadata-Version: 2.1
Name: transep
Version: 1.0.3
Summary: Transfer function hydrograph separation model (TRANSEP)
Home-page: https://transep.readthedocs.io
Author: Robin Schwemmle
Author-email: robin.schwemmle@hydrology.uni-freiburg.de
License: MIT
Classifier: Development Status :: 4 - Beta
Classifier: Intended Audience :: Science/Research
Classifier: License :: OSI Approved :: MIT License
Classifier: Programming Language :: Python :: 3
Classifier: Programming Language :: Python :: 3.7
Classifier: Programming Language :: Python :: 3.8
Classifier: Programming Language :: Python :: 3.9
Classifier: Programming Language :: Python :: Implementation :: CPython
Classifier: Topic :: Scientific/Engineering
Classifier: Operating System :: Microsoft :: Windows
Classifier: Operating System :: POSIX
Classifier: Operating System :: Unix
Classifier: Operating System :: MacOS
Requires-Python: >=3.7
License-File: LICENSE
Requires-Dist: numpy ==1.26.4
Requires-Dist: scipy ==1.13.1
